ls_wechat-1.0.data/scripts/ls.py
main/__init__.py
main/ls.py
ls_wechat-1.0.dist-info/LICENSE
ls_wechat-1.0.dist-info/METADATA
ls_wechat-1.0.dist-info/WHEEL
ls_wechat-1.0.dist-info/top_level.txt
ls_wechat-1.0.dist-info/RECORD
