Metadata-Version: 2.1
Name: ls-wechat
Version: 1.0
Summary: 微信自动发送消息脚本
Home-page: https://github.com/HiNoName/wechat_auto
Author: shuai_li
Author-email: 1216710774@qq.com
License: Apache License 2.0
Keywords: wechat,auto
Classifier: Development Status :: 5 - Production/Stable
Classifier: License :: OSI Approved :: Apache Software License
Classifier: Operating System :: OS Independent
Classifier: Programming Language :: Python :: 3.9
Requires-Python: >=3.7
License-File: LICENSE
Requires-Dist: pywin32
Requires-Dist: uiautomation (>=2.0.18)
